ytcomments/__init__.py
ytcomments-0.7.dist-info/LICENSE
ytcomments-0.7.dist-info/METADATA
ytcomments-0.7.dist-info/WHEEL
ytcomments-0.7.dist-info/entry_points.txt
ytcomments-0.7.dist-info/top_level.txt
ytcomments-0.7.dist-info/RECORD
